Workbook

Sheet Client DB
A1: BRAND | B1: No of Locations | C1: COMPANY | D1: CONTACT PERSON | E1: EMAIL | F1: DESIGNATION | G1: MOBILE | H1: ADDRESS | I1: STATE | J1: COUNTRY | K1: POST CODE | L1: CREATED ON | M1: SALES
A2: The Brew House & Bake & Brew Cafe | B2: 40 | C2: Movida Group | M2: MANFRED
A3: PappaRich | B3: 83 | C3: PappaRich Malaysia Sdn Bhd | M3: MANFRED
A4: Bhai Jim Jum | B4: 5 | C4: Jim Jum Thai Hotpot Restaurant | M4: MANFRED
A5: CoolBlog | B5: 290 | C5: Coolblog Enterprise Sdn Bhd | M5: MANFRED
A6: Kluang Station | B6: 200 | C6: Kluang Station F&B Sdn Bhd | M6: MANFRED
A7: He & She Coffee | B7: 30 | C7: He & She Coffee Sdn Bhd | M7: MANFRED
A8: Kopi Saigon | B8: 200 | C8: Seruni Global Sdn Bhd. | M8: MANFRED
A9: NOTA Cafe | B9: 3 | C9: Nota Concepts Setia Alam Sdn Bhd | M9: MANFRED
A10: Lotteria | B10: 1 | C10: Serai Group | M10: MANFRED
A11: Serai | C11: Serai Group | M11: MANFRED
A12: Serai Thai | C12: Serai Group | M12: MANFRED
A13: Jibby & Co | C13: Serai Group | M13: MANFRED
A14: Jibby Chow | C14: Serai Group | M14: MANFRED
A15: Jibby East Grill | C15: Serai Group | M15: MANFRED
A16: Super Blode | C16: Serai Group | M16: MANFRED
A17: Jibby by Park | C17: Serai Group | M17: MANFRED
A18: Chum Chum Pizzeria | C18: Serai Group | M18: MANFRED
A19: Iola | C19: Serai Group | M19: MANFRED
A20: Serai Café | C20: Serai Group | M20: MANFRED
A21: Meet Bros | C21: Serai Group | M21: MANFRED
A22: Makamakan | C22: Serai Group | M22: MANFRED
... A25: Serai Chicken Rice | C25: Serai Group | M25: MANFRED
A26: Nyonya Colors, Bad Scones | B26: 13 | C26: Little Cravings Sdn Bhd | M26: MANFRED
A27: Eco Disposable Sdn Bhd | B27: 1 | C27: Eco Disposable Sdn Bhd | M27: MANFRED
A28: Humblefood | B28: 5 | C28: Humble Food Holdings Sdn. Bhd | M28: MANFRED
A29: Red Kettle | B29: 2 | M29: MANFRED
A30: El Ocho | B30: 3 | M30: MANFRED
A31: Coast & Roast by Fish &Co. | B31: 1 | M31: MANFRED
A32: Third Serving | B32: 1 | M32: MANFRED
A33: Siti Li | B33: 1 | M33: MANFRED
A34: Ohcha Matcha | B34: 7 | M34: MANFRED
A35: Mokkys Pizza | B35: 9 | M35: MANFRED
A36: EM's | B36: 2 | M36: MANFRED
A37: Boost Juice | B37: 170 | M37: MANFRED
A38: Ayam Gepuk | B38: 46 | C38: Top Global Food And Beverages Sdn Bhd | M38: SYAZWAN
A39: Bebeks by Top Global | C39: Top Global Food And Beverages Sdn Bhd
A40: Nak Nak | B40: 7 | M40: MANFRED
A41: K Fry | B41: 10 | M41: MANFRED
A42: Boran | B42: 1 | M42: MANFRED
A43: Australian Bakery | B43: 1 | M43: MANFRED
A44: Mix Store | B44: 100 | M44: MANFRED
A45: DAO | B45: 13 | M45: MANFRED
A46: Triple Happiness | B46: 2 | M46: MANFRED
A47: Xin Mun Kee Freshmart | B47: 2 | M47: MANFRED
A48: Tangfei | B48: 3 | M48: MANFRED
A49: Happiness Asia Chicken | B49: 2 | M49: MANFRED
A50: Multi Venture | B50: 670 | C50: Multi Venture Networks Sdn Bhd | M50: SALES
A51: Yu Yi Herbs & Organic | B51: 2 | M51: MANFRED
A52: Purple Monkey | B52: 8 | M52: MANFRED
A53: Pasta Ohsem | B53: 6 | M53: MANFRED
A54: Arooi Thai Chicken | B54: 4 | M54: MANFRED
A55: Thai Moment | B55: 6 | M55: MANFRED
A56: 1978 Cucur Udang | B56: 10 | M56: MANFRED
A57: Pak Cu 916 | B57: 1 | C57: Pak Cu 916 | M57: SYAZWAN
A58: Karya Kopi | B58: 2 | C58: Jasai Enterprise Sdn Bhd | M58: SYAZWAN
A59: KUEH | B59: 4 | M59: SYAZWAN
A60: Little Days Cafe | B60: 1 | M60: MANFRED
A61: Uncle Lim's Kopitiam | B61: 3 | M61: MANFRED
A62: Yuen Ting Street Food | B62: 1 | M62: MANFRED
A63: All Ace | B63: 65 | M63: MANFRED
A64: Ribs King | B64: 2 | M64: MANFRED
A65: Taiwanese House | B65: 6 | M65: MANFRED
A66: Pad Boy | B66: 1 | M66: MANFRED
A67: Fluffed | B67: 4 | M67: MANFRED
A68: Khong Kee | B68: 1 | M68: MANFRED
A69: Harome | B69: 1 | M69: MANFRED
A70: Yoo Noodle | B70: 6 | M70: MANFRED
A71: Seirock-ya Ramen | B71: 9 | C71: Joypack Foods Malaysia | M71: SYAZWAN
A72: Cha-ba-shi-ra | B72: 1 | M72: MANFRED
A73: Dandy | B73: 5 | C73: Dandy Modern Food Sdn Bhd | M73: SYAZWAN
A74: Lim Fried Chicken | B74: 16 | M74: MANFRED
A75: Pak Tam | B75: 10 | M75: MANFRED
A76: Sari Ratu Signature | B76: 2 | C76: SDZ Dining Sdn Bhd | M76: SYAZWAN
A77: Mascorn Café | B77: 7 | C77: Mascorn Sdn Bhd | M77: SYAZWAN
A78: Happy Organic | C78: Mascorn Sdn Bhd | M78: SYAZWAN
A79: Ayam Gepuk Artisan | B79: 18 | M79: SYAZWAN
A80: Nasiiii.my | B80: 2 | M80: SYAZWAN
A81: Mee Tarik Jalan Sultan | B81: 6 | M81: SYAZWAN
A82: Mad Chilli Pan Mee | B82: 4 | M82: SYAZWAN
A83: Milk & Barley | B83: 6 | M83: SYAZWAN
A84: Kafe Ruuma | B84: 15 | C84: Kokos Sdn Bhd | M84: SYAZWAN
A85: Cocos | C85: Kokos Sdn Bhd
A86: JDV Cafe | B86: 3 | M86: MANFRED
A87: Meatpoint | B87: 12 | C87: Meatpoint | M87: MANFRED
A88: Sushi Point | C88: Meatpoint | M88: MANFRED
A89: Hott Point | C89: Meatpoint | M89: MANFRED
A90: Pizza Point | C90: Meatpoint | M90: MANFRED
A91: SeaPoint | C91: Meatpoint | M91: MANFRED
A92: Pretty Hot Chicken | C92: Meatpoint | M92: MANFRED
A93: Alpro Pharmacy | B93: 300 | M93: MANFRED
A94: Kopi Street | B94: 6 | L94: 46142 | M94: MANFRED
A95: Gula Cakery | B95: 20 | M95: MANFRED
A96: Michelangelo's | B96: 2 | C96: SW Food & Bar Concepts Sdn Bhd | M96: MANFRED
A97: Ocean Twe12ve | C97: SW Food & Bar Concepts Sdn Bhd | M97: MANFRED
A98: Pasta Fresca by Michelangelo's | C98: SW Food & Bar Concepts Sdn Bhd | M98: MANFRED
A99: La Juiceria | B99: 26 | C99: La Juiceria Superfoods Sdn Bhd | M99: MANFRED
A100: Super Saigon | C100: La Juiceria Superfoods Sdn Bhd | M100: MANFRED
A101: Hawker Hall | C101: La Juiceria Superfoods Sdn Bhd | M101: MANFRED
A102: Kampunglah | B102: 11 | C102: Kampung Salai Sdn Bhd | M102: MANFRED
...

Sheet Weekly Update
A1: DATE CREATED | B1: HUNTER | C1: COMPANY | D1: BRAND | E1: NO. OF LOCATION | F1: STATUS | G1: LAST CONTACT DATE | H1: CONTACT PERSON | I1: CONTACT TYPE | J1: NOTE | K1: FOLLOW UP REMINDER | L1: APPOINTMENT
A2: 46125 | B2: MANFRED | D2: Lotteria | F2: SUBSCRIBED | I2: FOLLOW UP MEETING | J2: Opening 2nd outlet in Sept 2026. | K2: 46223
A3: 46125 | B3: MANFRED | D3: Mee Tarik Jalan Sultan | F3: REJECTED | I3: STATUS UPDATE | K3: 46195
A4: 46125 | B4: MANFRED | D4: Dandy | F4: REJECTED | I4: FOLLOW UP CALL | K4: 46195
A5: 46125 | B5: MANFRED | D5: Ling Ling Long Long Gastrobar | F5: CONFIRMED | I5: FOLLOW UP CALL | J5: Still working on SI tagging | K5: 46223
A6: 46125 | B6: MANFRED | D6: Kissy Fish | F6: IN NEGO | I6: FOLLOW UP CALL | J6: Onboard 1st outlet Ling2 Long2 first. | K6: 46223
A7: 46125 | B7: MANFRED | D7: SuperNomms Fried Chicken | F7: PROPOSED | I7: FOLLOW UP CALL | J7: 6x outlets + 1x CK. Ops and CK head request for old quote and new quote to discuss with boss. | K7: 46223
A8: 46125 | B8: MANFRED | D8: Churros Plus | F8: KIV | I8: FOLLOW UP CALL | J8: FMH outlet average price is RM 1400/yr for 20 outlets. Setting meeting with client. | K8: 46223
A9: 46125 | B9: MANFRED | D9: Empire Sushi | F9: REJECTED | I9: FOLLOW UP CALL | K9: 46195
A10: 46125 | B10: MANFRED | D10: Tasty Chapathi | F10: IN NEGO | I10: FOLLOW UP CALL | J10: Did 2nd demo with client. Client to get back to us by end of the month to enjoy the previous quoted price. | K10: 46223
A11: 46125 | B11: MANFRED | D11: Sari Ratu Signature | F11: KIV | I11: FOLLOW UP CALL | J11: Client short of hand. Waiting for new staff to handle Bisync. | K11: 46223
A12: 46125 | B12: MANFRED | D12: Ali Muthu Ah Hock | F12: IN NEGO | I12: FOLLOW UP MEETING | J12: Following up with Edmund | K12: 46223
A13: 46125 | B13: MANFRED | D13: Michelangelo's | F13: PAID | I13: TRAINING | J13: Paid onboarding. Pending full payment after onboarded their SI and recipe. | K13: 46223
A14: 46125 | B14: MANFRED | D14: Dolly Dim Sum | F14: REJECTED | I14: FOLLOW UP CALL | K14: 46195
A15: 46125 | B15: MANFRED | D15: 1901 Hotdog Malaysia | F15: REJECTED | I15: FOLLOW UP CALL | K15: 46195
A16: 46006 | B16: DRA | D16: 4Fingers Crispy Chicken | F16: PROSPECT | I16: OFFLINE PRESENTATION | J16: MEETING WITH TEAM NEXT ROUND | K16: 46135
A17: 46146 | B17: KHAFIZ | D17: Cor Blimey | F17: REJECTED | I17: SALES MEETING | J17: 1st meeting on 4/5
A18: 46146 | B18: KHAFIZ | D18: Rendezvous Steak House | F18: REJECTED | I18: COLD CALL
A19: 46146 | B19: KHAFIZ | D19: Karaa Saraam | F19: LEAD | I19: COLD CALL
A20: 46146 | B20: KHAFIZ | D20: Sushi Zanmai | F20: LEAD | I20: EMAIL BLAST
A21: 46146 | B21: KHAFIZ | D21: Two Sons | F21: LEAD | I21: EMAIL BLAST
A22: 46146 | B22: KHAFIZ | D22: Oriental Kopi | F22: LEAD | I22: EMAIL BLAST
A23: 46146 | B23: KHAFIZ | D23: Hidang KL | F23: LEAD | I23: COLD CALL
A24: 46146 | B24: KHAFIZ | D24: Social | F24: LEAD | I24: EMAIL BLAST
A25: 46146 | B25: KHAFIZ | D25: Kampung Lah | F25: LEAD | I25: COLD CALL
A26: 46146 | B26: KHAFIZ | D26: Sushi King | F26: LEAD | I26: EMAIL BLAST | J26: Manage to get outlet manager number.will contact the pic and try to connect with the HQ side | K26: 46176
A27: 46146 | B27: KHAFIZ | D27: Baan 26 | F27: LEAD | I27: EMAIL BLAST
A28: 46146 | B28: KHAFIZ | D28: Sate Hut | F28: LEAD | I28: COLD CALL
A29: 46146 | B29: KHAFIZ | D29: Sate Haji Samuri | F29: REJECTED | I29: SALES MEETING | J29: Send Proposal to client
A30: 46146 | B30: MANFRED | D30: Hallaway | F30: PROPOSED | I30: FOLLOW UP MEETING | J30: Sent out quote for client to discuss with mgmt. / Follow up but no feedback from the top management | K30: 46223
A31: 46146 | B31: MANFRED | D31: OHO Thai Mookata & Bar | F31: PROPOSED | I31: FOLLOW UP MEETING | J31: Sent out quote for client to discuss with mgmt. | K31: 46223
A32: 46146 | B32: MANFRED | D32: Farmer and Chef Hotpot | F32: PROPOSED | I32: FOLLOW UP MEETING | J32: Sent out quote for client to discuss with mgmt. | K32: 46223
A33: 46146 | B33: MANFRED | D33: Ayam Gepuk Hut | F33: PROSPECT | I33: FOLLOW UP MEETING | J33: Waiting for client to share info to send out quote and set 2nd meeting with their bosses. | K33: 46223
A34: 46146 | B34: MANFRED | D34: Samudra Food | F34: PROSPECT | I34: FOLLOW UP MEETING | J34: Waiting for client to pass us their recipe details to onboard a demo process flow of PMS and set 2nd meeting with them. | K34: 46223
A35: 46146 | B35: MANFRED | D35: Big Onion Catering | F35: PROSPECT | I35: FOLLOW UP MEETING | J35: Reach out to Shah/Louise and no respond on call/text. Continue to reach out to them both. | K35: 46223
A36: 46146 | B36: MANFRED | D36: Kluang Rail Coffee | F36: LEAD | I36: FOLLOW UP MEETING | J36: Setting meeting. | K36: 46223
A37: 46146 | B37: MANFRED | D37: Kopi Street | F37: LEAD | I37: FOLLOW UP MEETING | J37: Setting meeting. | K37: 46223
A38: 46146 | B38: MANFRED | D38: Shihlin Taiwan Street Snacks | F38: REJECTED | I38: STATUS UPDATE | J38: SG HQ not considering this for now. | K38: 46198
A39: 46146 | B39: MANFRED | D39: BHC Chicken | F39: PROSPECT | I39: FOLLOW UP MEETING | J39: Send out proposal quote of 3 years for client. Client verbally wants to start onboarding on August 2026. | K39: 46223
A40: 46147 | B40: KHAFIZ | D40: House Of Kambing | F40: REJECTED | I40: DEMO | J40: Demo Set on 13/5 | K40: 46153
A41: 46153 | B41: KHAFIZ | D41: Coffee Boy | F41: REJECTED | J41: Meet with one of the operation manager.but Manfred already reach out to them
A42: 46153 | B42: KHAFIZ | D42: Locca Cafe | F42: REJECTED | I42: DEMO | J42: 1st Meeting on 4th June/Meet with Alif owner one of the franchise.currently happy with the flow just looking at something else which is POS system.pass another contact og his aquintance . and already send quotation
A43: 46153 | B43: MANFRED | D43: VCR | F43: PROSPECT | I43: FOLLOW UP MEETING | J43: Boss to arrange meeting with ops head for demo. | K43: 46223
A44: 46153 | B44: MANFRED | D44: Thai Bistro | F44: PROSPECT | I44: DEMO | J44: CEO says onboard and train Ling2 Long2 outlets first before decide for new brand outlets. | K44: 46224
A45: 46160 | B45: KHAFIZ | D45: Bask Bear | F45: LEAD | I45: EMAIL BLAST
A46: 46160 | B46: KHAFIZ | D46: Planet Nasi Kukus | F46: REJECTED | I46: COLD CALL | J46: Upfront rejected
A47: 46160 | B47: KHAFIZ | D47: Ayam Gepuk Boss | F47: LEAD | I47: COLD CALL | J47: talk with the operation manager.ask to send details first
A48: 46160 | B48: KHAFIZ | D48: My Ayam Ketuk | F48: REJECTED | I48: COLD CALL | J48: Rejected
A49: 46160 | B49: MANFRED | D49: Belike | F49: PROSPECT | I49: DEMO | J49: Client put us on hold to focus on 1st outlet and new Zeoniq POS. | K49: 46224
A50: 46160 | B50: MANFRED | D50: Asia Pacific University | F50: PROSPECT | I50: FOLLOW UP MEETING | J50: Setting demo meeting with operation head | K50: 46224
A51: 46160 | B51: MANFRED | D51: Lao Tao Ke | F51: KIV | I51: FOLLOW UP CALL | J51: Setting demo meeting with operation head | K51: 46224
A52: 46160 | B52: MANFRED | D52: Syarikat Kopi Kok | F52: LEAD | I52: FOLLOW UP MEETING | J52: Setting demo meeting with the boss | K52: 46224
A53: 46167 | B53: KHAFIZ | D53: Sate Zul | F53: LEAD | I53: COLD CALL | K53: 46176
A54: 46167 | B54: KHAFIZ | D54: Penang Cendul | F54: LEAD | I54: COLD CALL | K54: 46176
A55: 46167 | B55: KHAFIZ | D55: Ayam Pak Sheikh | F55: REJECTED | I55: DEMO | J55: 1st meeting on 4th June / Reschedule to 11/6/1st Demo done,Positive feedback from the PIC , basicly settle the the issue what they curretnly have .will send proposal on 12/6 | K55: 46189
A56: 46167 | B56: KHAFIZ | D56: Ayam Gepuk Pak Gendut | F56: LEAD | I56: COLD CALL | J56: Have thier own POS | K56: 46167
A57: 46167 | B57: MANFRED | D57: Kyochon | F57: LEAD | I57: FOLLOW UP CALL | J57: Using Feedme POS + Inventory. Setting meeting with Teddy and Terry. | K57: 46224
A58: 46167 | B58: MANFRED | D58: Sugar Bun | F58: REJECTED | I58: FOLLOW UP CALL | J58: Using P Cloud system, a cloud based server to store all their datas. | K58: 46198
A59: 46167 | B59: MANFRED | D59: Black Bixon | F59: LEAD | I59: FOLLOW UP MEETING | J59: Setting demo meeting with operation head | K59: 46224
A60: 46167 | B60: MANFRED | D60: Abang Adik Kopitiam | F60: PROSPECT | I60: FOLLOW UP CALL | J60: Quote to send out to client once gotten the detail. | K60: 46224
A61: 46171 | B61: MANFRED | D61: Ippudo | F61: LEAD | I61: COLD CALL | J61: Using Zeoniq | K61: 46224
A62: 46171 | B62: MANFRED | D62: Absolute Thai | F62: LEAD | I62: COLD CALL | J62: Using Zeoniq | K62: 46224
A63: 46171 | B63: MANFRED | D63: Mee Tarik Faizal Kong | F63: REJECTED | I63: COLD CALL | J63: Using Hubbo POS. Management in cost cutting and lack of manpower. Business not doing well. | K63: 46198
A64: 46171 | B64: MANFRED | D64: Black Canyon | F64: REJECTED | I64: COLD CALL | J64: Client using Zeoniq + Codemax | K64: 46198
A65: 46171 | B65: MANFRED | D65: Johnny's Restaurant | F65: REJECTED | I65: COLD CALL | J65: Client using Zeoniq + Codemax | K65: 46198
A66: 46171 | B66: KHAFIZ | D66: Park's Bagel | F66: LEAD | I66: COLD CALL | J66: Spoke with the outlet staff currently have 5 outlets.MAnage to get the manager number | K66: 46176
... A70: 46171 | B70: KHAFIZ | D70: Ayam Gepuk Papa Jon | F70: LEAD | I70: COLD CALL | J70: Have 10 outlets | K70: 46176
A71: 46171 | B71: KHAFIZ | D71: Luna Luna | F71: LEAD | I71: COLD CALL | K71: 46176
A72: 46171 | B72: KHAFIZ | D72: Tsujuki Sushi | F72: LEAD | I72: COLD CALL | K72: 46176
A73: 46202 | B73: KHAFIZ | D73: Milk & Barley | F73: REJECTED | I73: COLD CALL | J73: Spoke with the outlet staff , will forawrd the details to the HQ eam | K73: 46176
A74: 46171 | B74: MANFRED | D74: Slim Chicken | F74: PROSPECT | I74: FOLLOW UP MEETING | J74: Setting meeting with Ashraf | K74: 46224
A75: 46177 | B75: KHAFIZ | D75: Pak John Steamboat | F75: LEAD | I75: COLD CALL | J75: Spoke with Anuwar outlet Manager , will inform HQ and follow up 4/6 evening | K75: 46178
A76: 46178 | B76: KHAFIZ | D76: Potato Corner | F76: LEAD | I76: EMAIL BLAST | J76: Went to the store in IOI Damansara.Staff send gave email
A77: 46178 | B77: KHAFIZ | D77: Nak Nak | F77: LEAD | I77: EMAIL BLAST | J77: Went to the store staff said send email to HQ
A78: 46181 | B78: KHAFIZ | D78: Nasi Lemak Burung Hantu | F78: LEAD | I78: COLD CALL | J78: Got the contact during canvassing / Call on 8/6 but no reposnd
A79: 46181 | B79: KHAFIZ | D79: Pretty Hot Chicken | F79: LEAD | I79: COLD CALL | J79: Got the contact during canvassing
A80: 46181 | B80: KHAFIZ | D80: Hot Bird | F80: LEAD | I80: COLD CALL | J80: Got the contact during canvassing
A81: 46181 | B81: MANFRED | D81: Ticco Malaysia | F81: LEAD | I81: FOLLOW UP MEETING | J81: 10x outlets + 1x CK. Following up to set a demo meeting. Met ops manager in IOI Dsara Mall and seems quite keen on the solution. | K81: 46224
A82: 46181 | B82: MANFRED | D82: Kim Yong Gee (HK Signature Beef Noodle) | F82: LEAD | I82: FOLLOW UP CALL | J82: Following up to set a demo meeting. Met outlet manager in SS15 Subang canvassing. | K82: 46224
A83: 46182 | B83: KHAFIZ | D83: Red Kettle | F83: REJECTED | I83: COLD CALL | J83: Went to the outlet.spoke with the Owner.Currently have 2 outltes/1ck.Currently using Xilnex for POS and POS is including Inventory as well.Not looking to change the system.
A84: 46205 | B84: KHAFIZ | D84: Arest | F84: KIV | I84: DEMO | J84: When to the outlet and follow up with ameer.The owner are focusing on operation side for the next 6 months
A85: 46202 | B85: KHAFIZ | D85: Rasa Nostra Coffee | F85: LEAD | I85: COLD CALL | J85: have 6 Outlet (Franchise) and 1 CK.But CK is only for coffee Beans , main HQ in Kelana jaya distribute pes to all of the outlet . MAnage to spoke with Ira.Eventually shes on the sales side.She will pass the number PIC from the procument | K85: 46203
A86: 46184 | B86: KHAFIZ | D86: Ayam Gepuk Legacy | F86: LEAD | I86: COLD CALL
A87: 46188 | B87: MANFRED | D87: TY Food | F87: LEAD | I87: FOLLOW UP MEETING | J87: Met with the BD Manager. Their set up in MY is not ready until Q4. TBC. | K87: 46224
A88: 46188 | B88: MANFRED | D88: Dodo Seafood Treats Malaysia | F88: KIV | I88: FOLLOW UP MEETING | J88: Client only deal with 10 distributors from 10 different states. Easy to manage their trading orders from distributors using accounting system. Own another brand called Crusty | K88: 46224
A89: 46203 | B89: KHAFIZ | D89: Sun Thai Food | F89: LEAD | I89: COLD CALL | J89: Spoke With the head chef , currently they have 6 outlet 1 CK and they have another brand called Palo by sunthai food.Already inform to hr and boss.need to call the hr.Already called HQ send introduction about Bisync. | K89: 46209
A90: 46203 | B90: KHAFIZ | D90: Palo By Sun Thai Food | F90: LEAD | I90: COLD CALL
A91: 46192 | B91: KHAFIZ | D91: Lynn's Catering | F91: LEAD | I91: COLD CALL
A92: 46192 | B92: KHAFIZ | D92: Parathai | F92: LEAD | I92: COLD CALL | J92: 20 outlets for KL and JB 1 CK . They plan their delivery for outlets outside of klang valley. staff pass their HQ number to contact PIC
A93: 46192 | B93: KHAFIZ | D93: Jibril | F93: LEAD | I93: FOLLOW UP MEETING | J93: 6 outlets + 1CK . Meeting on 24/6
A94: 46192 | B94: MANFRED | D94: Santan | F94: KIV | I94: FOLLOW UP MEETING | J94: 3x outlets. Closed down canteen business in Red Q. Not looking for any solution for now. | K94: 46224
A95: 46192 | B95: MANFRED | D95: Krispy Kreme | F95: PROSPECT | I95: FOLLOW UP CALL | J95: Gotten the emails from KK. To send out the quotes for 2 years, 3mths + 1mth payment to Nadia & Jessica | K95: 46224
A96: 46192 | B96: KHAFIZ | D96: Zui De Yi | F96: REJECTED | I96: DEMO
A97: 46202 | B97: KHAFIZ | D97: Ayam Gepuk Express | F97: LEAD | I97: COLD CALL | J97: 15 Outlets | K97: 46203
A98: 46195 | B98: KHAFIZ | D98: Ayam Gepuk Ori Selayang | F98: LEAD | I98: EMAIL BLAST
A99: 46217 | B99: KHAFIZ | D99: Ayam Gepuk Tok Mat | F99: REJECTED | I99: COLD CALL | J99: Have 40 outlets. Half of them are manage by HQ.1 warehouse.They develope their own inventory system | K99: 46216
A100: 46195 | B100: KHAFIZ | D100: Ayam Gepuk Pak Raden | F100: LEAD | I100: COLD CALL
A101: 46210 | B101: KHAFIZ | D101: Kopiesatu | F101: PROSPECT | I101: COLD CALL | J101: Already follow up with Atiqah.They going to have another 41 outlets upcoming. Currenty all staff busy preparing for MAHA event.will follow up again and its going to be longshot.Went to FDM and manage to get Manager contact | K101: 46234
A102: 46202 | B102: KHAFIZ | D102: Ayam Penyet AP | F102: LEAD | I102: EMAIL BLAST
A103: 46199 | B103: MANFRED | D103: Daily Bekal | F103: PROSPECT | I103: DEMO | J103: To send out the quote today. Client to decide by end of June. | K103: 46224
...

Sheet SYS LST
A1: Johor | B1: 0. LEAD | C1: COLD CALL | D1: EUGENE | E1: SUBSCRIPTION FEE | F1: MALAYSIA
A2: Kedah | B2: 1. PROSPECT | C2: EMAIL BLAST | D2: MANFRED | E2: CUSTOMIZATION | F2: SINGAPORE
A3: Kelantan | B3: 2. PROPOSED | C3: FOLLOW UP CALL | D3: WAN | E3: DEPOSIT
A4: Malacca | B4: 3. IN NEGO | C4: FOLLOW UP EMAIL | D4: DRA | E4: SUBSCRIPTION BALANCE
A5: Negeri Sembilan | B5: 4. CONFIRMED | C5: SALES MEETING | D5: TERRENCE | E5: SUPPORT FEE
A6: Pahang | B6: 5. INVOICED | C6: FOLLOW UP MEETING | D6: LENNY | E6: TRAINING
A7: Penang | B7: 6. PAID | C7: DEMO | D7: KHAFIZ
A8: Perak | B8: 7. SUBSCRIBED | C8: ONLINE PRESENTATION
A9: Perlis | B9: 8. KIV | C9: OFFLINE PRESENTATION | D9: ALL
A10: Sabah | B10: 9. REJECTED | C10: STATUS UPDATE
A11: Sarawak | C11: TRAINING
A12: Selangor | C12: POST MEETING
A13: Terengganu | C13: REGULAR CATCH UP
A14: Kuala Lumpur | C14: PAYMENT RECEIVED
A15: Putrajaya | C15: SUBCRIPTION STARTS
A16: Labuan

Sheet SUMMARY
A2: From | B2: =B3-(E2*7) -> 45985 | D2: NO OF WEEKS | E2: 20
A3: To | B3: 46125
A5: ACTIVITY | B5: ALL | C5: EUGENE | D5: MANFRED | E5: WAN | H5: DRA | J5: STATUS UPDATE
A6: ='SYS LST'!C1 -> COLD CALL | B6: =COUNTIFS('Weekly Update'!$A:$A,">="&SUMMARY!$B$2,'Weekly Update'!$A:$A,"<="&SUMMARY!$B$3,'Weekly Update'!$I:$I,A$6) -> 0 | C6: =COUNTIFS('Weekly Update'!$A:$A,">="&SUMMARY!$B$2,'Weekly Update'!$A:$A,"<="&SUMMARY!$B$3,'Weekly Update'!$I:$I,$A6,'Weekly Update'!$B:$B,SUMMARY!$C$5) -> 0 | D6: =COUNTIFS('Weekly Update'!$A:$A,">="&SUMMARY!$B$2,'Weekly Update'!$A:$A,"<="&SUMMARY!$B$3,'Weekly Update'!$I:$I,$A6,'Weekly Update'!$B:$B,SUMMARY!$D$5) -> 0 | E6: =COUNTIFS('Weekly Update'!$A:$A,">="&SUMMARY!$B$2,'Weekly Update'!$A:$A,"<="&SUMMARY!$B$3,'Weekly Update'!$I:$I,$A6,'Weekly Update'!$B:$B,SUMMARY!$E$5) -> 0 | F6: =COUNTIFS('Weekly Update'!$A:$A,">="&SUMMARY!$B$2,'Weekly Update'!$A:$A,"<="&SUMMARY!$B$3,'Weekly Update'!$I:$I,$A6,'Weekly Update'!$B:$B,SUMMARY!$F$5) -> 0 | G6: =COUNTIFS('Weekly Update'!$A:$A,">="&SUMMARY!$B$2,'Weekly Update'!$A:$A,"<="&SUMMARY!$B$3,'Weekly Update'!$I:$I,$A6,'Weekly Update'!$B:$B,SUMMARY!$G$5) -> 0 | H6: =COUNTIFS('Weekly Update'!$A:$A,">="&SUMMARY!$B$2,'Weekly Update'!$A:$A,"<="&SUMMARY!$B$3,'Weekly Update'!$I:$I,$A6,'Weekly Update'!$B:$B,SUMMARY!$H$5) -> 0 | J6: 0. LEAD | K6: =COUNTIFS('Weekly Update'!$A:$A,">="&SUMMARY!$B$2,'Weekly Update'!$A:$A,"<="&SUMMARY!$B$3,'Weekly Update'!$I:$I,$J$5,'Weekly Update'!$F:$F,$J6) -> 0
A7: ='SYS LST'!C2 -> EMAIL BLAST | B7: =COUNTIFS('Weekly Update'!$A:$A,">="&SUMMARY!$B$2,'Weekly Update'!$A:$A,"<="&SUMMARY!$B$3,'Weekly Update'!$I:$I,A7) -> 0 | C7: =COUNTIFS('Weekly Update'!$A:$A,">="&SUMMARY!$B$2,'Weekly Update'!$A:$A,"<="&SUMMARY!$B$3,'Weekly Update'!$I:$I,$A7,'Weekly Update'!$B:$B,SUMMARY!$C$5) -> 0 | D7: =COUNTIFS('Weekly Update'!$A:$A,">="&SUMMARY!$B$2,'Weekly Update'!$A:$A,"<="&SUMMARY!$B$3,'Weekly Update'!$I:$I,$A7,'Weekly Update'!$B:$B,SUMMARY!$D$5) -> 0 | E7: =COUNTIFS('Weekly Update'!$A:$A,">="&SUMMARY!$B$2,'Weekly Update'!$A:$A,"<="&SUMMARY!$B$3,'Weekly Update'!$I:$I,$A7,'Weekly Update'!$B:$B,SUMMARY!$E$5) -> 0 | F7: =COUNTIFS('Weekly Update'!$A:$A,">="&SUMMARY!$B$2,'Weekly Update'!$A:$A,"<="&SUMMARY!$B$3,'Weekly Update'!$I:$I,$A7,'Weekly Update'!$B:$B,SUMMARY!$F$5) -> 0 | G7: =COUNTIFS('Weekly Update'!$A:$A,">="&SUMMARY!$B$2,'Weekly Update'!$A:$A,"<="&SUMMARY!$B$3,'Weekly Update'!$I:$I,$A7,'Weekly Update'!$B:$B,SUMMARY!$G$5) -> 0 | H7: =COUNTIFS('Weekly Update'!$A:$A,">="&SUMMARY!$B$2,'Weekly Update'!$A:$A,"<="&SUMMARY!$B$3,'Weekly Update'!$I:$I,$A7,'Weekly Update'!$B:$B,SUMMARY!$H$5) -> 0 | J7: 1. PROSPECT | K7: =COUNTIFS('Weekly Update'!$A:$A,">="&SUMMARY!$B$2,'Weekly Update'!$A:$A,"<="&SUMMARY!$B$3,'Weekly Update'!$I:$I,$J$5,'Weekly Update'!$F:$F,$J7) -> 0
A8: ='SYS LST'!C3 -> FOLLOW UP CALL | B8: =COUNTIFS('Weekly Update'!$A:$A,">="&SUMMARY!$B$2,'Weekly Update'!$A:$A,"<="&SUMMARY!$B$3,'Weekly Update'!$I:$I,A8) -> 10 | C8: =COUNTIFS('Weekly Update'!$A:$A,">="&SUMMARY!$B$2,'Weekly Update'!$A:$A,"<="&SUMMARY!$B$3,'Weekly Update'!$I:$I,$A8,'Weekly Update'!$B:$B,SUMMARY!$C$5) -> 0 | D8: =COUNTIFS('Weekly Update'!$A:$A,">="&SUMMARY!$B$2,'Weekly Update'!$A:$A,"<="&SUMMARY!$B$3,'Weekly Update'!$I:$I,$A8,'Weekly Update'!$B:$B,SUMMARY!$D$5) -> 10 | E8: =COUNTIFS('Weekly Update'!$A:$A,">="&SUMMARY!$B$2,'Weekly Update'!$A:$A,"<="&SUMMARY!$B$3,'Weekly Update'!$I:$I,$A8,'Weekly Update'!$B:$B,SUMMARY!$E$5) -> 0 | F8: =COUNTIFS('Weekly Update'!$A:$A,">="&SUMMARY!$B$2,'Weekly Update'!$A:$A,"<="&SUMMARY!$B$3,'Weekly Update'!$I:$I,$A8,'Weekly Update'!$B:$B,SUMMARY!$F$5) -> 0 | G8: =COUNTIFS('Weekly Update'!$A:$A,">="&SUMMARY!$B$2,'Weekly Update'!$A:$A,"<="&SUMMARY!$B$3,'Weekly Update'!$I:$I,$A8,'Weekly Update'!$B:$B,SUMMARY!$G$5) -> 0 | H8: =COUNTIFS('Weekly Update'!$A:$A,">="&SUMMARY!$B$2,'Weekly Update'!$A:$A,"<="&SUMMARY!$B$3,'Weekly Update'!$I:$I,$A8,'Weekly Update'!$B:$B,SUMMARY!$H$5) -> 0 | J8: 2. PROPOSED | K8: =COUNTIFS('Weekly Update'!$A:$A,">="&SUMMARY!$B$2,'Weekly Update'!$A:$A,"<="&SUMMARY!$B$3,'Weekly Update'!$I:$I,$J$5,'Weekly Update'!$F:$F,$J8) -> 0
A9: ='SYS LST'!C4 -> FOLLOW UP EMAIL | B9: =COUNTIFS('Weekly Update'!$A:$A,">="&SUMMARY!$B$2,'Weekly Update'!$A:$A,"<="&SUMMARY!$B$3,'Weekly Update'!$I:$I,A9) -> 0 | C9: =COUNTIFS('Weekly Update'!$A:$A,">="&SUMMARY!$B$2,'Weekly Update'!$A:$A,"<="&SUMMARY!$B$3,'Weekly Update'!$I:$I,$A9,'Weekly Update'!$B:$B,SUMMARY!$C$5) -> 0 | D9: =COUNTIFS('Weekly Update'!$A:$A,">="&SUMMARY!$B$2,'Weekly Update'!$A:$A,"<="&SUMMARY!$B$3,'Weekly Update'!$I:$I,$A9,'Weekly Update'!$B:$B,SUMMARY!$D$5) -> 0 | E9: =COUNTIFS('Weekly Update'!$A:$A,">="&SUMMARY!$B$2,'Weekly Update'!$A:$A,"<="&SUMMARY!$B$3,'Weekly Update'!$I:$I,$A9,'Weekly Update'!$B:$B,SUMMARY!$E$5) -> 0 | F9: =COUNTIFS('Weekly Update'!$A:$A,">="&SUMMARY!$B$2,'Weekly Update'!$A:$A,"<="&SUMMARY!$B$3,'Weekly Update'!$I:$I,$A9,'Weekly Update'!$B:$B,SUMMARY!$F$5) -> 0 | G9: =COUNTIFS('Weekly Update'!$A:$A,">="&SUMMARY!$B$2,'Weekly Update'!$A:$A,"<="&SUMMARY!$B$3,'Weekly Update'!$I:$I,$A9,'Weekly Update'!$B:$B,SUMMARY!$G$5) -> 0 | H9: =COUNTIFS('Weekly Update'!$A:$A,">="&SUMMARY!$B$2,'Weekly Update'!$A:$A,"<="&SUMMARY!$B$3,'Weekly Update'!$I:$I,$A9,'Weekly Update'!$B:$B,SUMMARY!$H$5) -> 0 | J9: 3. CONFIRMED | K9: =COUNTIFS('Weekly Update'!$A:$A,">="&SUMMARY!$B$2,'Weekly Update'!$A:$A,"<="&SUMMARY!$B$3,'Weekly Update'!$I:$I,$J$5,'Weekly Update'!$F:$F,$J9) -> 0
A10: ='SYS LST'!C5 -> SALES MEETING | B10: =COUNTIFS('Weekly Update'!$A:$A,">="&SUMMARY!$B$2,'Weekly Update'!$A:$A,"<="&SUMMARY!$B$3,'Weekly Update'!$I:$I,A10) -> 0 | C10: =COUNTIFS('Weekly Update'!$A:$A,">="&SUMMARY!$B$2,'Weekly Update'!$A:$A,"<="&SUMMARY!$B$3,'Weekly Update'!$I:$I,$A10,'Weekly Update'!$B:$B,SUMMARY!$C$5) -> 0 | D10: =COUNTIFS('Weekly Update'!$A:$A,">="&SUMMARY!$B$2,'Weekly Update'!$A:$A,"<="&SUMMARY!$B$3,'Weekly Update'!$I:$I,$A10,'Weekly Update'!$B:$B,SUMMARY!$D$5) -> 0 | E10: =COUNTIFS('Weekly Update'!$A:$A,">="&SUMMARY!$B$2,'Weekly Update'!$A:$A,"<="&SUMMARY!$B$3,'Weekly Update'!$I:$I,$A10,'Weekly Update'!$B:$B,SUMMARY!$E$5) -> 0 | F10: =COUNTIFS('Weekly Update'!$A:$A,">="&SUMMARY!$B$2,'Weekly Update'!$A:$A,"<="&SUMMARY!$B$3,'Weekly Update'!$I:$I,$A10,'Weekly Update'!$B:$B,SUMMARY!$F$5) -> 0 | G10: =COUNTIFS('Weekly Update'!$A:$A,">="&SUMMARY!$B$2,'Weekly Update'!$A:$A,"<="&SUMMARY!$B$3,'Weekly Update'!$I:$I,$A10,'Weekly Update'!$B:$B,SUMMARY!$G$5) -> 0 | H10: =COUNTIFS('Weekly Update'!$A:$A,">="&SUMMARY!$B$2,'Weekly Update'!$A:$A,"<="&SUMMARY!$B$3,'Weekly Update'!$I:$I,$A10,'Weekly Update'!$B:$B,SUMMARY!$H$5) -> 0 | J10: 4. POC | K10: =COUNTIFS('Weekly Update'!$A:$A,">="&SUMMARY!$B$2,'Weekly Update'!$A:$A,"<="&SUMMARY!$B$3,'Weekly Update'!$I:$I,$J$5,'Weekly Update'!$F:$F,$J10) -> 0
A11: ='SYS LST'!C6 -> FOLLOW UP MEETING | B11: =COUNTIFS('Weekly Update'!$A:$A,">="&SUMMARY!$B$2,'Weekly Update'!$A:$A,"<="&SUMMARY!$B$3,'Weekly Update'!$I:$I,A11) -> 2 | C11: =COUNTIFS('Weekly Update'!$A:$A,">="&SUMMARY!$B$2,'Weekly Update'!$A:$A,"<="&SUMMARY!$B$3,'Weekly Update'!$I:$I,$A11,'Weekly Update'!$B:$B,SUMMARY!$C$5) -> 0 | D11: =COUNTIFS('Weekly Update'!$A:$A,">="&SUMMARY!$B$2,'Weekly Update'!$A:$A,"<="&SUMMARY!$B$3,'Weekly Update'!$I:$I,$A11,'Weekly Update'!$B:$B,SUMMARY!$D$5) -> 2 | E11: =COUNTIFS('Weekly Update'!$A:$A,">="&SUMMARY!$B$2,'Weekly Update'!$A:$A,"<="&SUMMARY!$B$3,'Weekly Update'!$I:$I,$A11,'Weekly Update'!$B:$B,SUMMARY!$E$5) -> 0 | F11: =COUNTIFS('Weekly Update'!$A:$A,">="&SUMMARY!$B$2,'Weekly Update'!$A:$A,"<="&SUMMARY!$B$3,'Weekly Update'!$I:$I,$A11,'Weekly Update'!$B:$B,SUMMARY!$F$5) -> 0 | G11: =COUNTIFS('Weekly Update'!$A:$A,">="&SUMMARY!$B$2,'Weekly Update'!$A:$A,"<="&SUMMARY!$B$3,'Weekly Update'!$I:$I,$A11,'Weekly Update'!$B:$B,SUMMARY!$G$5) -> 0 | H11: =COUNTIFS('Weekly Update'!$A:$A,">="&SUMMARY!$B$2,'Weekly Update'!$A:$A,"<="&SUMMARY!$B$3,'Weekly Update'!$I:$I,$A11,'Weekly Update'!$B:$B,SUMMARY!$H$5) -> 0 | J11: 5. INVOICED | K11: =COUNTIFS('Weekly Update'!$A:$A,">="&SUMMARY!$B$2,'Weekly Update'!$A:$A,"<="&SUMMARY!$B$3,'Weekly Update'!$I:$I,$J$5,'Weekly Update'!$F:$F,$J11) -> 0
A12: ='SYS LST'!C7 -> DEMO | B12: =COUNTIFS('Weekly Update'!$A:$A,">="&SUMMARY!$B$2,'Weekly Update'!$A:$A,"<="&SUMMARY!$B$3,'Weekly Update'!$I:$I,A12) -> 0 | C12: =COUNTIFS('Weekly Update'!$A:$A,">="&SUMMARY!$B$2,'Weekly Update'!$A:$A,"<="&SUMMARY!$B$3,'Weekly Update'!$I:$I,$A12,'Weekly Update'!$B:$B,SUMMARY!$C$5) -> 0 | D12: =COUNTIFS('Weekly Update'!$A:$A,">="&SUMMARY!$B$2,'Weekly Update'!$A:$A,"<="&SUMMARY!$B$3,'Weekly Update'!$I:$I,$A12,'Weekly Update'!$B:$B,SUMMARY!$D$5) -> 0 | E12: =COUNTIFS('Weekly Update'!$A:$A,">="&SUMMARY!$B$2,'Weekly Update'!$A:$A,"<="&SUMMARY!$B$3,'Weekly Update'!$I:$I,$A12,'Weekly Update'!$B:$B,SUMMARY!$E$5) -> 0 | F12: =COUNTIFS('Weekly Update'!$A:$A,">="&SUMMARY!$B$2,'Weekly Update'!$A:$A,"<="&SUMMARY!$B$3,'Weekly Update'!$I:$I,$A12,'Weekly Update'!$B:$B,SUMMARY!$F$5) -> 0 | G12: =COUNTIFS('Weekly Update'!$A:$A,">="&SUMMARY!$B$2,'Weekly Update'!$A:$A,"<="&SUMMARY!$B$3,'Weekly Update'!$I:$I,$A12,'Weekly Update'!$B:$B,SUMMARY!$G$5) -> 0 | H12: =COUNTIFS('Weekly Update'!$A:$A,">="&SUMMARY!$B$2,'Weekly Update'!$A:$A,"<="&SUMMARY!$B$3,'Weekly Update'!$I:$I,$A12,'Weekly Update'!$B:$B,SUMMARY!$H$5) -> 0 | J12: 6. PAID | K12: =COUNTIFS('Weekly Update'!$A:$A,">="&SUMMARY!$B$2,'Weekly Update'!$A:$A,"<="&SUMMARY!$B$3,'Weekly Update'!$I:$I,$J$5,'Weekly Update'!$F:$F,$J12) -> 0
A13: ='SYS LST'!C8 -> ONLINE PRESENTATION | B13: =COUNTIFS('Weekly Update'!$A:$A,">="&SUMMARY!$B$2,'Weekly Update'!$A:$A,"<="&SUMMARY!$B$3,'Weekly Update'!$I:$I,A13) -> 0 | C13: =COUNTIFS('Weekly Update'!$A:$A,">="&SUMMARY!$B$2,'Weekly Update'!$A:$A,"<="&SUMMARY!$B$3,'Weekly Update'!$I:$I,$A13,'Weekly Update'!$B:$B,SUMMARY!$C$5) -> 0 | D13: =COUNTIFS('Weekly Update'!$A:$A,">="&SUMMARY!$B$2,'Weekly Update'!$A:$A,"<="&SUMMARY!$B$3,'Weekly Update'!$I:$I,$A13,'Weekly Update'!$B:$B,SUMMARY!$D$5) -> 0 | E13: =COUNTIFS('Weekly Update'!$A:$A,">="&SUMMARY!$B$2,'Weekly Update'!$A:$A,"<="&SUMMARY!$B$3,'Weekly Update'!$I:$I,$A13,'Weekly Update'!$B:$B,SUMMARY!$E$5) -> 0 | F13: =COUNTIFS('Weekly Update'!$A:$A,">="&SUMMARY!$B$2,'Weekly Update'!$A:$A,"<="&SUMMARY!$B$3,'Weekly Update'!$I:$I,$A13,'Weekly Update'!$B:$B,SUMMARY!$F$5) -> 0 | G13: =COUNTIFS('Weekly Update'!$A:$A,">="&SUMMARY!$B$2,'Weekly Update'!$A:$A,"<="&SUMMARY!$B$3,'Weekly Update'!$I:$I,$A13,'Weekly Update'!$B:$B,SUMMARY!$G$5) -> 0 | H13: =COUNTIFS('Weekly Update'!$A:$A,">="&SUMMARY!$B$2,'Weekly Update'!$A:$A,"<="&SUMMARY!$B$3,'Weekly Update'!$I:$I,$A13,'Weekly Update'!$B:$B,SUMMARY!$H$5) -> 0 | J13: 7. SUBSCRIBED | K13: =COUNTIFS('Weekly Update'!$A:$A,">="&SUMMARY!$B$2,'Weekly Update'!$A:$A,"<="&SUMMARY!$B$3,'Weekly Update'!$I:$I,$J$5,'Weekly Update'!$F:$F,$J13) -> 0
A14: ='SYS LST'!C9 -> OFFLINE PRESENTATION | B14: =COUNTIFS('Weekly Update'!$A:$A,">="&SUMMARY!$B$2,'Weekly Update'!$A:$A,"<="&SUMMARY!$B$3,'Weekly Update'!$I:$I,A14) -> 1 | C14: =COUNTIFS('Weekly Update'!$A:$A,">="&SUMMARY!$B$2,'Weekly Update'!$A:$A,"<="&SUMMARY!$B$3,'Weekly Update'!$I:$I,$A14,'Weekly Update'!$B:$B,SUMMARY!$C$5) -> 0 | D14: =COUNTIFS('Weekly Update'!$A:$A,">="&SUMMARY!$B$2,'Weekly Update'!$A:$A,"<="&SUMMARY!$B$3,'Weekly Update'!$I:$I,$A14,'Weekly Update'!$B:$B,SUMMARY!$D$5) -> 0 | E14: =COUNTIFS('Weekly Update'!$A:$A,">="&SUMMARY!$B$2,'Weekly Update'!$A:$A,"<="&SUMMARY!$B$3,'Weekly Update'!$I:$I,$A14,'Weekly Update'!$B:$B,SUMMARY!$E$5) -> 0 | F14: =COUNTIFS('Weekly Update'!$A:$A,">="&SUMMARY!$B$2,'Weekly Update'!$A:$A,"<="&SUMMARY!$B$3,'Weekly Update'!$I:$I,$A14,'Weekly Update'!$B:$B,SUMMARY!$F$5) -> 0 | G14: =COUNTIFS('Weekly Update'!$A:$A,">="&SUMMARY!$B$2,'Weekly Update'!$A:$A,"<="&SUMMARY!$B$3,'Weekly Update'!$I:$I,$A14,'Weekly Update'!$B:$B,SUMMARY!$G$5) -> 0 | H14: =COUNTIFS('Weekly Update'!$A:$A,">="&SUMMARY!$B$2,'Weekly Update'!$A:$A,"<="&SUMMARY!$B$3,'Weekly Update'!$I:$I,$A14,'Weekly Update'!$B:$B,SUMMARY!$H$5) -> 1 | J14: 8. KIV | K14: =COUNTIFS('Weekly Update'!$A:$A,">="&SUMMARY!$B$2,'Weekly Update'!$A:$A,"<="&SUMMARY!$B$3,'Weekly Update'!$I:$I,$J$5,'Weekly Update'!$F:$F,$J14) -> 0
A15: ='SYS LST'!C10 -> STATUS UPDATE | B15: =COUNTIFS('Weekly Update'!$A:$A,">="&SUMMARY!$B$2,'Weekly Update'!$A:$A,"<="&SUMMARY!$B$3,'Weekly Update'!$I:$I,A15) -> 1 | C15: =COUNTIFS('Weekly Update'!$A:$A,">="&SUMMARY!$B$2,'Weekly Update'!$A:$A,"<="&SUMMARY!$B$3,'Weekly Update'!$I:$I,$A15,'Weekly Update'!$B:$B,SUMMARY!$C$5) -> 0 | D15: =COUNTIFS('Weekly Update'!$A:$A,">="&SUMMARY!$B$2,'Weekly Update'!$A:$A,"<="&SUMMARY!$B$3,'Weekly Update'!$I:$I,$A15,'Weekly Update'!$B:$B,SUMMARY!$D$5) -> 1 | E15: =COUNTIFS('Weekly Update'!$A:$A,">="&SUMMARY!$B$2,'Weekly Update'!$A:$A,"<="&SUMMARY!$B$3,'Weekly Update'!$I:$I,$A15,'Weekly Update'!$B:$B,SUMMARY!$E$5) -> 0 | F15: =COUNTIFS('Weekly Update'!$A:$A,">="&SUMMARY!$B$2,'Weekly Update'!$A:$A,"<="&SUMMARY!$B$3,'Weekly Update'!$I:$I,$A15,'Weekly Update'!$B:$B,SUMMARY!$F$5) -> 0 | G15: =COUNTIFS('Weekly Update'!$A:$A,">="&SUMMARY!$B$2,'Weekly Update'!$A:$A,"<="&SUMMARY!$B$3,'Weekly Update'!$I:$I,$A15,'Weekly Update'!$B:$B,SUMMARY!$G$5) -> 0 | H15: =COUNTIFS('Weekly Update'!$A:$A,">="&SUMMARY!$B$2,'Weekly Update'!$A:$A,"<="&SUMMARY!$B$3,'Weekly Update'!$I:$I,$A15,'Weekly Update'!$B:$B,SUMMARY!$H$5) -> 0 | J15: 9. REJECTED | K15: =COUNTIFS('Weekly Update'!$A:$A,">="&SUMMARY!$B$2,'Weekly Update'!$A:$A,"<="&SUMMARY!$B$3,'Weekly Update'!$I:$I,$J$5,'Weekly Update'!$F:$F,$J15) -> 0
A16: ='SYS LST'!C11 -> TRAINING | B16: =COUNTIFS('Weekly Update'!$A:$A,">="&SUMMARY!$B$2,'Weekly Update'!$A:$A,"<="&SUMMARY!$B$3,'Weekly Update'!$I:$I,A16) -> 1 | C16: =COUNTIFS('Weekly Update'!$A:$A,">="&SUMMARY!$B$2,'Weekly Update'!$A:$A,"<="&SUMMARY!$B$3,'Weekly Update'!$I:$I,$A16,'Weekly Update'!$B:$B,SUMMARY!$C$5) -> 0 | D16: =COUNTIFS('Weekly Update'!$A:$A,">="&SUMMARY!$B$2,'Weekly Update'!$A:$A,"<="&SUMMARY!$B$3,'Weekly Update'!$I:$I,$A16,'Weekly Update'!$B:$B,SUMMARY!$D$5) -> 1 | E16: =COUNTIFS('Weekly Update'!$A:$A,">="&SUMMARY!$B$2,'Weekly Update'!$A:$A,"<="&SUMMARY!$B$3,'Weekly Update'!$I:$I,$A16,'Weekly Update'!$B:$B,SUMMARY!$E$5) -> 0 | F16: =COUNTIFS('Weekly Update'!$A:$A,">="&SUMMARY!$B$2,'Weekly Update'!$A:$A,"<="&SUMMARY!$B$3,'Weekly Update'!$I:$I,$A16,'Weekly Update'!$B:$B,SUMMARY!$F$5) -> 0 | G16: =COUNTIFS('Weekly Update'!$A:$A,">="&SUMMARY!$B$2,'Weekly Update'!$A:$A,"<="&SUMMARY!$B$3,'Weekly Update'!$I:$I,$A16,'Weekly Update'!$B:$B,SUMMARY!$G$5) -> 0 | H16: =COUNTIFS('Weekly Update'!$A:$A,">="&SUMMARY!$B$2,'Weekly Update'!$A:$A,"<="&SUMMARY!$B$3,'Weekly Update'!$I:$I,$A16,'Weekly Update'!$B:$B,SUMMARY!$H$5) -> 0
A17: ='SYS LST'!C12 -> POST MEETING | B17: =COUNTIFS('Weekly Update'!$A:$A,">="&SUMMARY!$B$2,'Weekly Update'!$A:$A,"<="&SUMMARY!$B$3,'Weekly Update'!$I:$I,A17) -> 0 | C17: =COUNTIFS('Weekly Update'!$A:$A,">="&SUMMARY!$B$2,'Weekly Update'!$A:$A,"<="&SUMMARY!$B$3,'Weekly Update'!$I:$I,$A17,'Weekly Update'!$B:$B,SUMMARY!$C$5) -> 0 | D17: =COUNTIFS('Weekly Update'!$A:$A,">="&SUMMARY!$B$2,'Weekly Update'!$A:$A,"<="&SUMMARY!$B$3,'Weekly Update'!$I:$I,$A17,'Weekly Update'!$B:$B,SUMMARY!$D$5) -> 0 | E17: =COUNTIFS('Weekly Update'!$A:$A,">="&SUMMARY!$B$2,'Weekly Update'!$A:$A,"<="&SUMMARY!$B$3,'Weekly Update'!$I:$I,$A17,'Weekly Update'!$B:$B,SUMMARY!$E$5) -> 0 | F17: =COUNTIFS('Weekly Update'!$A:$A,">="&SUMMARY!$B$2,'Weekly Update'!$A:$A,"<="&SUMMARY!$B$3,'Weekly Update'!$I:$I,$A17,'Weekly Update'!$B:$B,SUMMARY!$F$5) -> 0 | G17: =COUNTIFS('Weekly Update'!$A:$A,">="&SUMMARY!$B$2,'Weekly Update'!$A:$A,"<="&SUMMARY!$B$3,'Weekly Update'!$I:$I,$A17,'Weekly Update'!$B:$B,SUMMARY!$G$5) -> 0 | H17: =COUNTIFS('Weekly Update'!$A:$A,">="&SUMMARY!$B$2,'Weekly Update'!$A:$A,"<="&SUMMARY!$B$3,'Weekly Update'!$I:$I,$A17,'Weekly Update'!$B:$B,SUMMARY!$H$5) -> 0
A18: ='SYS LST'!C13 -> REGULAR CATCH UP | B18: =COUNTIFS('Weekly Update'!$A:$A,">="&SUMMARY!$B$2,'Weekly Update'!$A:$A,"<="&SUMMARY!$B$3,'Weekly Update'!$I:$I,A18) -> 0 | C18: =COUNTIFS('Weekly Update'!$A:$A,">="&SUMMARY!$B$2,'Weekly Update'!$A:$A,"<="&SUMMARY!$B$3,'Weekly Update'!$I:$I,$A18,'Weekly Update'!$B:$B,SUMMARY!$C$5) -> 0 | D18: =COUNTIFS('Weekly Update'!$A:$A,">="&SUMMARY!$B$2,'Weekly Update'!$A:$A,"<="&SUMMARY!$B$3,'Weekly Update'!$I:$I,$A18,'Weekly Update'!$B:$B,SUMMARY!$D$5) -> 0 | E18: =COUNTIFS('Weekly Update'!$A:$A,">="&SUMMARY!$B$2,'Weekly Update'!$A:$A,"<="&SUMMARY!$B$3,'Weekly Update'!$I:$I,$A18,'Weekly Update'!$B:$B,SUMMARY!$E$5) -> 0 | F18: =COUNTIFS('Weekly Update'!$A:$A,">="&SUMMARY!$B$2,'Weekly Update'!$A:$A,"<="&SUMMARY!$B$3,'Weekly Update'!$I:$I,$A18,'Weekly Update'!$B:$B,SUMMARY!$F$5) -> 0 | G18: =COUNTIFS('Weekly Update'!$A:$A,">="&SUMMARY!$B$2,'Weekly Update'!$A:$A,"<="&SUMMARY!$B$3,'Weekly Update'!$I:$I,$A18,'Weekly Update'!$B:$B,SUMMARY!$G$5) -> 0 | H18: =COUNTIFS('Weekly Update'!$A:$A,">="&SUMMARY!$B$2,'Weekly Update'!$A:$A,"<="&SUMMARY!$B$3,'Weekly Update'!$I:$I,$A18,'Weekly Update'!$B:$B,SUMMARY!$H$5) -> 0
A19: ='SYS LST'!C14 -> PAYMENT RECEIVED | B19: =COUNTIFS('Weekly Update'!$A:$A,">="&SUMMARY!$B$2,'Weekly Update'!$A:$A,"<="&SUMMARY!$B$3,'Weekly Update'!$I:$I,A19) -> 0 | C19: =COUNTIFS('Weekly Update'!$A:$A,">="&SUMMARY!$B$2,'Weekly Update'!$A:$A,"<="&SUMMARY!$B$3,'Weekly Update'!$I:$I,$A19,'Weekly Update'!$B:$B,SUMMARY!$C$5) -> 0 | D19: =COUNTIFS('Weekly Update'!$A:$A,">="&SUMMARY!$B$2,'Weekly Update'!$A:$A,"<="&SUMMARY!$B$3,'Weekly Update'!$I:$I,$A19,'Weekly Update'!$B:$B,SUMMARY!$D$5) -> 0 | E19: =COUNTIFS('Weekly Update'!$A:$A,">="&SUMMARY!$B$2,'Weekly Update'!$A:$A,"<="&SUMMARY!$B$3,'Weekly Update'!$I:$I,$A19,'Weekly Update'!$B:$B,SUMMARY!$E$5) -> 0 | F19: =COUNTIFS('Weekly Update'!$A:$A,">="&SUMMARY!$B$2,'Weekly Update'!$A:$A,"<="&SUMMARY!$B$3,'Weekly Update'!$I:$I,$A19,'Weekly Update'!$B:$B,SUMMARY!$F$5) -> 0 | G19: =COUNTIFS('Weekly Update'!$A:$A,">="&SUMMARY!$B$2,'Weekly Update'!$A:$A,"<="&SUMMARY!$B$3,'Weekly Update'!$I:$I,$A19,'Weekly Update'!$B:$B,SUMMARY!$G$5) -> 0 | H19: =COUNTIFS('Weekly Update'!$A:$A,">="&SUMMARY!$B$2,'Weekly Update'!$A:$A,"<="&SUMMARY!$B$3,'Weekly Update'!$I:$I,$A19,'Weekly Update'!$B:$B,SUMMARY!$H$5) -> 0
A20: ='SYS LST'!C15 -> SUBCRIPTION STARTS | B20: =COUNTIFS('Weekly Update'!$A:$A,">="&SUMMARY!$B$2,'Weekly Update'!$A:$A,"<="&SUMMARY!$B$3,'Weekly Update'!$I:$I,A20) -> 0 | C20: =COUNTIFS('Weekly Update'!$A:$A,">="&SUMMARY!$B$2,'Weekly Update'!$A:$A,"<="&SUMMARY!$B$3,'Weekly Update'!$I:$I,$A20,'Weekly Update'!$B:$B,SUMMARY!$C$5) -> 0 | D20: =COUNTIFS('Weekly Update'!$A:$A,">="&SUMMARY!$B$2,'Weekly Update'!$A:$A,"<="&SUMMARY!$B$3,'Weekly Update'!$I:$I,$A20,'Weekly Update'!$B:$B,SUMMARY!$D$5) -> 0 | E20: =COUNTIFS('Weekly Update'!$A:$A,">="&SUMMARY!$B$2,'Weekly Update'!$A:$A,"<="&SUMMARY!$B$3,'Weekly Update'!$I:$I,$A20,'Weekly Update'!$B:$B,SUMMARY!$E$5) -> 0 | F20: =COUNTIFS('Weekly Update'!$A:$A,">="&SUMMARY!$B$2,'Weekly Update'!$A:$A,"<="&SUMMARY!$B$3,'Weekly Update'!$I:$I,$A20,'Weekly Update'!$B:$B,SUMMARY!$F$5) -> 0 | G20: =COUNTIFS('Weekly Update'!$A:$A,">="&SUMMARY!$B$2,'Weekly Update'!$A:$A,"<="&SUMMARY!$B$3,'Weekly Update'!$I:$I,$A20,'Weekly Update'!$B:$B,SUMMARY!$G$5) -> 0 | H20: =COUNTIFS('Weekly Update'!$A:$A,">="&SUMMARY!$B$2,'Weekly Update'!$A:$A,"<="&SUMMARY!$B$3,'Weekly Update'!$I:$I,$A20,'Weekly Update'!$B:$B,SUMMARY!$H$5) -> 0
